mkdocs_nbstore/__init__.py
mkdocs_nbstore/converter.py
mkdocs_nbstore/figure.py
mkdocs_nbstore/logger.py
mkdocs_nbstore/markdown.py
mkdocs_nbstore/plugin.py
mkdocs_nbstore-0.3.0.dist-info/METADATA
mkdocs_nbstore-0.3.0.dist-info/WHEEL
mkdocs_nbstore-0.3.0.dist-info/entry_points.txt
mkdocs_nbstore-0.3.0.dist-info/licenses/LICENSE
mkdocs_nbstore-0.3.0.dist-info/RECORD
