Metadata-Version: 2.4
Name: mkdocs-nbstore
Version: 0.3.0
Summary: A MkDocs plugin for seamlessly embedding Jupyter notebook visualizations into documentation with simple Markdown syntax
Project-URL: Documentation, https://daizutabi.github.io/mkdocs-nbstore/
Project-URL: Source, https://github.com/daizutabi/mkdocs-nbstore
Project-URL: Issues, https://github.com/daizutabi/mkdocs-nbstore/issues
Author-email: daizutabi <daizutabi@gmail.com>
License: MIT License
License-File: LICENSE
Keywords: jupyter,mkdocs,notebook
Classifier: Development Status :: 4 - Beta
Classifier: Programming Language :: Python
Classifier: Programming Language :: Python :: 3.10
Classifier: Programming Language :: Python :: 3.11
Classifier: Programming Language :: Python :: 3.12
Classifier: Programming Language :: Python :: 3.13
Classifier: Topic :: Documentation
Classifier: Topic :: Software Development :: Documentation
Classifier: Topic :: Text Processing :: Markup :: Markdown
Requires-Python: >=3.10
Requires-Dist: mkdocs>=1.6
Requires-Dist: nbstore>=0.3.1
